pylabolt/__init__.py
pylabolt/pylabolt.py
pylabolt/base/__init__.py
pylabolt/base/boundary.py
pylabolt/base/boundaryConditions.py
pylabolt/base/boundaryConditions_cuda.py
pylabolt/base/lattice.py
pylabolt/base/mesh.py
pylabolt/base/obstacle.py
pylabolt/base/obstacleTypes.py
pylabolt/base/schemeLB.py
pylabolt/base/setRegionFields.py
pylabolt/base/models/MRT_params.py
pylabolt/base/models/__init__.py
pylabolt/base/models/collisionModels.py
pylabolt/base/models/collisionModels_cuda.py
pylabolt/base/models/equilibriumModels.py
pylabolt/base/models/equilibriumModels_cuda.py
pylabolt/base/models/forcingModels.py
pylabolt/base/models/forcingModels_cuda.py
pylabolt/parallel/MPI_comm.py
pylabolt/parallel/MPI_decompose.py
pylabolt/parallel/MPI_reconstruct.py
pylabolt/parallel/__init__.py
pylabolt/parallel/cudaReduce.py
pylabolt/parallel/parallelSetup.py
pylabolt/solvers/__init__.py
pylabolt/solvers/fluidLB/__init__.py
pylabolt/solvers/fluidLB/baseAlgorithm.py
pylabolt/solvers/fluidLB/createSim.py
pylabolt/solvers/fluidLB/deviceFields.py
pylabolt/solvers/fluidLB/fields.py
pylabolt/solvers/fluidLB/fluidLB.py
pylabolt/solvers/fluidLB/initFields.py
pylabolt/solvers/fluidLB/kernels.py
pylabolt/utils/__init__.py
pylabolt/utils/inputOutput.py
pylabolt/utils/options.py
pylabolt/utils/vtkconvert.py
pylabolt-0.2.0.dist-info/LICENSE
pylabolt-0.2.0.dist-info/METADATA
pylabolt-0.2.0.dist-info/WHEEL
pylabolt-0.2.0.dist-info/entry_points.txt
pylabolt-0.2.0.dist-info/top_level.txt
pylabolt-0.2.0.dist-info/zip-safe
pylabolt-0.2.0.dist-info/RECORD
